MANIFEST.in
README
requirements.txt
setup.py
ezrpc/__init__.py
ezrpc/client.py
ezrpc/registry.py
ezrpc/server.py
ezrpc/server_worker.py
ezrpc.egg-info/PKG-INFO
ezrpc.egg-info/SOURCES.txt
ezrpc.egg-info/dependency_links.txt
ezrpc.egg-info/requires.txt
ezrpc.egg-info/top_level.txt