Metadata-Version: 1.0
Name: ezrpc
Version: 0.1.0
Summary: Easy to use ZeroMQ based RPC library
Home-page: http://github.com/abh1nav/ezrpc/
Author: Abhinav Ajgaonkar
Author-email: abhinav316@gmail.com
License: Apache 2.0 License
Platform: UNKNOWN
